pysmurf-2.0.1.dist-info/licenses/LICENSE
smurf/__helper__.py
smurf/__init__.py
smurf/model.py
smurf/spatial_object.py
smurf/split.py
smurf/unroll.py
pysmurf-2.0.1.dist-info/METADATA
pysmurf-2.0.1.dist-info/WHEEL
pysmurf-2.0.1.dist-info/top_level.txt
pysmurf-2.0.1.dist-info/RECORD
