Metadata-Version: 2.4
Name: pysmurf
Version: 2.0.1
Summary: Segmentation and Manifold UnRolling Framework (SMURF)
Author: Juanru Guo
Author-email: g.juanru@wustl.edu
Requires-Python: >=3.8
License-File: LICENSE
Requires-Dist: numpy>=1.26.4
Requires-Dist: pandas>=1.5.3
Requires-Dist: tqdm
Requires-Dist: scanpy>=1.10.0
Requires-Dist: scipy>=1.12.0
Requires-Dist: matplotlib>=3.8.3
Requires-Dist: numba>=0.59.0
Requires-Dist: scikit-learn>=1.4.1
Requires-Dist: Pillow>=10.2.0
Requires-Dist: anndata>=0.10.6
Requires-Dist: h5py>=3.10.0
Requires-Dist: pyarrow>=16.1.0
Requires-Dist: igraph>=0.11.5
Requires-Dist: shapely>=2.0.3
Provides-Extra: full
Requires-Dist: torch>=2.2.1; extra == "full"
Requires-Dist: py3nvml>=0.2.7; extra == "full"
Dynamic: author
Dynamic: author-email
Dynamic: description
Dynamic: description-content-type
Dynamic: license-file
Dynamic: provides-extra
Dynamic: requires-dist
Dynamic: requires-python
Dynamic: summary
